openapi2jsonschema_ng/__init__.py
openapi2jsonschema_ng/command.py
openapi2jsonschema_ng/errors.py
openapi2jsonschema_ng/log.py
openapi2jsonschema_ng/test_command.py
openapi2jsonschema_ng/util.py
openapi2jsonschema_ng-0.9.0.dist-info/LICENSE
openapi2jsonschema_ng-0.9.0.dist-info/METADATA
openapi2jsonschema_ng-0.9.0.dist-info/WHEEL
openapi2jsonschema_ng-0.9.0.dist-info/entry_points.txt
openapi2jsonschema_ng-0.9.0.dist-info/RECORD
