Metadata-Version: 2.1
Name: openapi2jsonschema_ng
Version: 0.9.0
Summary: A utility to extract JSON Schema from a valid OpenAPI specification
Home-page: https://gitlab.com/nirvati/openapi2jsonschema
License: Apache-2.0
Keywords: openapi,jsonschema
Author: Gareth Rushgrove
Author-email: gareth@morethanseven.net
Requires-Python: >=3.8,<4.0
Classifier: License :: OSI Approved :: Apache Software License
Classifier: Programming Language :: Python :: 3
Classifier: Programming Language :: Python :: 3.8
Classifier: Programming Language :: Python :: 3.9
Classifier: Programming Language :: Python :: 3.10
Classifier: Programming Language :: Python :: 3.11
Requires-Dist: click (>=8.0,<9.0)
Requires-Dist: colorama (>=0.4.1,<0.5.0)
Requires-Dist: jsonref (>=1,<2)
Requires-Dist: pyyaml (>=6,<7)
Project-URL: Repository, https://gitlab.com/nirvati/openapi2jsonschema
